setup.py
dimagi/__init__.py
dimagi/test_utils/__init__.py
dimagi/test_utils/base.py
dimagi/test_utils/cache_tests.py
dimagi/utils/__init__.py
dimagi/utils/chunked.py
dimagi/utils/create_unique_filter.py
dimagi/utils/csv.py
dimagi/utils/dates.py
dimagi/utils/excel.py
dimagi/utils/excel_importer.py
dimagi/utils/export.py
dimagi/utils/filehash.py
dimagi/utils/gitinfo.py
dimagi/utils/gmailloghandler.py
dimagi/utils/html.py
dimagi/utils/indicators.py
dimagi/utils/logging.py
dimagi/utils/make_time.py
dimagi/utils/make_uuid.py
dimagi/utils/mixins.py
dimagi/utils/models.py
dimagi/utils/modules.py
dimagi/utils/multithreading.py
dimagi/utils/parsing.py
dimagi/utils/passgen.py
dimagi/utils/post.py
dimagi/utils/prime_views.py
dimagi/utils/printing.py
dimagi/utils/queryable_set.py
dimagi/utils/read_only.py
dimagi/utils/repo.py
dimagi/utils/requestskit.py
dimagi/utils/retryable_task.py
dimagi/utils/reversessh.py
dimagi/utils/subprocess_timeout.py
dimagi/utils/system.py
dimagi/utils/threadlocals.py
dimagi/utils/timeout.py
dimagi/utils/uptime_monitor.py
dimagi/utils/web.py
dimagi/utils/couch/__init__.py
dimagi/utils/couch/bulk.py
dimagi/utils/couch/changes.py
dimagi/utils/couch/database.py
dimagi/utils/couch/delete.py
dimagi/utils/couch/lazy_attachment_doc.py
dimagi/utils/couch/loosechange.py
dimagi/utils/couch/pagination.py
dimagi/utils/couch/resource_conflict.py
dimagi/utils/couch/safe_index.py
dimagi/utils/couch/settingshelper.py
dimagi/utils/couch/sync_docs.py
dimagi/utils/couch/tastykit.py
dimagi/utils/couch/testrunner.py
dimagi/utils/couch/uid.py
dimagi/utils/couch/undo.py
dimagi/utils/couch/cache/__init__.py
dimagi/utils/couch/cache/cache_core/__init__.py
dimagi/utils/couch/cache/cache_core/api.py
dimagi/utils/couch/cache/cache_core/const.py
dimagi/utils/couch/cache/cache_core/gen.py
dimagi/utils/couch/cache/cache_core/lib.py
dimagi/utils/couch/debugdb/__init__.py
dimagi/utils/couch/debugdb/debugdatabase.py
dimagi/utils/data/__init__.py
dimagi/utils/data/crud.py
dimagi_utils.egg-info/PKG-INFO
dimagi_utils.egg-info/SOURCES.txt
dimagi_utils.egg-info/dependency_links.txt
dimagi_utils.egg-info/requires.txt
dimagi_utils.egg-info/top_level.txt