Metadata-Version: 1.0
Name: dimagi-utils
Version: 1.2.0
Summary: Dimagi Shared Utilities
Home-page: http://www.dimagi.com/
Author: Dimagi
Author-email: dev@dimagi.com
License: UNKNOWN
Platform: UNKNOWN
